examples/basic_usage.py
tests/config.py
tests/test_api.py
unifi_sm_api/__init__.py
unifi_sm_api/api.py
unifi_sm_api-0.2.1.dist-info/licenses/LICENSE
unifi_sm_api-0.2.1.dist-info/METADATA
unifi_sm_api-0.2.1.dist-info/WHEEL
unifi_sm_api-0.2.1.dist-info/top_level.txt
unifi_sm_api-0.2.1.dist-info/RECORD
