Metadata-Version: 2.4
Name: unifi-sm-api
Version: 0.2.1
Summary: Python library for interacting with UniFi Site Manager API
Author-email: Jokob Sk <jokob.sk@gmail.com>
License: MIT
Requires-Python: >=3.8
License-File: LICENSE
Requires-Dist: requests>=2.0
Dynamic: license-file
